dbxdriverack/__init__.py
dbxdriverack/py.typed
dbxdriverack/pa2/__init__.py
dbxdriverack/pa2/autoeq.py
dbxdriverack/pa2/compressor.py
dbxdriverack/pa2/crossover.py
dbxdriverack/pa2/feedback.py
dbxdriverack/pa2/generator.py
dbxdriverack/pa2/geq.py
dbxdriverack/pa2/indelay.py
dbxdriverack/pa2/limiter.py
dbxdriverack/pa2/outputband.py
dbxdriverack/pa2/outputdelay.py
dbxdriverack/pa2/peq.py
dbxdriverack/pa2/rta.py
dbxdriverack/pa2/subharmonic.py
dbxdriverack-0.0.4.dist-info/LICENSE.txt
dbxdriverack-0.0.4.dist-info/METADATA
dbxdriverack-0.0.4.dist-info/WHEEL
dbxdriverack-0.0.4.dist-info/top_level.txt
dbxdriverack-0.0.4.dist-info/RECORD
