Metadata-Version: 2.1
Name: dbxdriverack
Version: 0.0.4
Summary: Python client library for communicating with dbx DriveRack loudspeaker management systems
Author-email: Matt Kupferman <matt@kupferman.net>
Maintainer-email: Matt Kupferman <matt@kupferman.net>
License: MIT License
Project-URL: Homepage, https://github.com/mkupferman/dbxdriverack-python
Project-URL: Documentation, https://mkupferman.github.io/dbxdriverack-python/
Classifier: Programming Language :: Python :: 3
Classifier: License :: OSI Approved :: MIT License
Classifier: Operating System :: OS Independent
Classifier: Intended Audience :: Developers
Classifier: Development Status :: 4 - Beta
Requires-Python: >=3.11
License-File: LICENSE.txt
Requires-Dist: tssplit
Provides-Extra: dev
Requires-Dist: black; extra == "dev"
Provides-Extra: validate
Requires-Dist: mypy; extra == "validate"
Provides-Extra: docs
Requires-Dist: sphinx; extra == "docs"
Requires-Dist: sphinxcontrib-napoleon; extra == "docs"
Requires-Dist: sphinx-rtd-theme; extra == "docs"
